lpsds/__init__.py
lpsds/handlers.py
lpsds/inout.py
lpsds/logger.py
lpsds/metrics.py
lpsds/mlflow.py
lpsds/model.py
lpsds/notebook.py
lpsds/operation.py
lpsds/preprocessing.py
lpsds/utils.py
lpsds-0.20.0.dist-info/LICENSE
lpsds-0.20.0.dist-info/METADATA
lpsds-0.20.0.dist-info/WHEEL
lpsds-0.20.0.dist-info/top_level.txt
lpsds-0.20.0.dist-info/RECORD
