Metadata-Version: 2.1
Name: lpsds
Version: 0.20.0
Summary: Helper functions for data science projects.
Home-page: https://github.com/rctorres/fast-ds
Author: Rodrigo Coura Torres
Author-email: torres.rc@gmail.com
Project-URL: Bug Tracker, https://github.com/rctorres/fast-ds/issues
Classifier: Programming Language :: Python :: 3
Classifier: License :: OSI Approved :: MIT License
Classifier: Operating System :: OS Independent
Requires-Python: >=3.6
License-File: LICENSE
